fubar.py
setup.py
fubar.egg-info/PKG-INFO
fubar.egg-info/SOURCES.txt
fubar.egg-info/dependency_links.txt
fubar.egg-info/requires.txt
fubar.egg-info/top_level.txt