Metadata-Version: 1.0
Name: fubar
Version: 0.3.0
Summary: PBKDF2-AES-CTR-HMAC-SHA256-RSA-PKCS#1-OAEP-PSS-bencode wrapper
Home-page: UNKNOWN
Author: UNKNOWN
Author-email: UNKNOWN
License: MIT
Platform: UNKNOWN
